{"info":{"team type":null,"cutoff":1630.0,"cutoff deviation":0,"metagame":"gen2ubers","number of battles":1179},"data":{"Jolteon":{"Moves":{"bodyslam":0.0,"agility":0.0,"curse":0.0,"thunderbolt":0.0,"hiddenpowerice":0.0,"hiddenpowerwater":23.3553987456,"thunder":23.3553987456,"hiddenpowergrass":0.0,"batonpass":23.3553987456,"protect":0.0,"rest":0.0,"skullbash":0.0,"thunderwave":0.0,"growth":23.3553987456,"hiddenpowerfighting":0.0,"doublekick":0.0,"toxic":0.0},"Checks and Counters":{},"Abilities":{"noability":23.3553987456},"Teammates":{"Golem":0.0,"Cloyster":21.958033064,"Tyranitar":6.6928285729,"Snorlax":21.958033064,"Marowak":0.0,"Charizard":0.0,"Forretress":0.0,"Miltank":0.0,"Pikachu":0.0,"Jynx":0.0,"Mewtwo":21.958033064,"Rhydon":15.2652044911,"Mew":21.958033064,"Exeggutor":0.0,"Blissey":0.0,"empty":0.0,"Nidorino":0.0,"Zapdos":0.0,"Steelix":0.0,"Misdreavus":0.0,"Lapras":0.0,"Gengar":0.0,"Lugia":0.0,"Aerodactyl":0.0,"Charmeleon":0.0,"Ho-Oh":0.0,"Sandslash":0.0,"Umbreon":0.0,"Celebi":0.0,"Arcanine":0.0,"Skarmory":0.0,"Nidoking":0.0,"Heracross":0.0,"Feraligatr":0.0,"Blastoise":0.0},"usage":0.4207164,"Items":{"nothing":0.0,"leftovers":23.3553987456,"berserkgene":0.0,"kingsrock":0.0,"mintberry":0.0},"Raw count":231,"Spreads":{"Serious:252\/252\/252\/252\/252\/252":23.3553987456,"Serious:252\/0\/252\/252\/252\/252":0.0},"Happiness":{"255":23.3553987456},"Viability Ceiling":[15,78,78,74]},"Cloyster":{"Moves":{"clamp":0.0,"icywind":23.8853226366,"hiddenpowerdragon":0.0,"blizzard":0.0,"rest":0.0,"hiddenpowerelectric":0.0,"hiddenpowerfire":0.4944420319,"hiddenpowerfighting":0.0,"icebeam":0.0,"return":0.0,"substitute":0.0,"":0.0,"curse":0.0,"hiddenpowerpsychic":0.0,"hiddenpowerdark":0.0,"triattack":0.0,"hiddenpowergrass":0.0,"toxic":3.7877308812,"surf":28.1674955496,"explosion":28.1674955496,"barrier":0.0,"reflect":0.0,"raindance":0.0,"hiddenpowerground":0.0,"protect":0.0,"spikes":28.1674955496,"screech":0.0,"spikecannon":0.0,"endure":0.0,"doubleedge":0.0,"rapidspin":0.0,"bide":0.0,"hiddenpowerrock":0.0},"Checks and Counters":{},"Abilities":{"noability":28.1674955496},"Teammates":{"Golem":0.0,"Pinsir":0.0,"Gengar":0.0482071607,"Quagsire":0.0,"Vaporeon":0.0,"Tyranitar":9.0353296366,"Snorlax":26.4557527884,"Raikou":1.3695915597,"Feraligatr":0.0,"Muk":0.0,"Machamp":0.0,"Marowak":0.529923891,"Zapdos":2.5982042738,"Raichu":0.0,"Porygon2":0.0,"Ampharos":0.0,"Miltank":0.0,"Pikachu":0.0,"Jynx":0.0,"Mewtwo":26.4557527884,"Rhydon":15.2652044911,"Chansey":0.0,"Exeggutor":0.0,"Blissey":0.0,"empty":0.0,"Smeargle":0.0,"Aerodactyl":0.0,"Starmie":0.0,"Heracross":0.0,"Entei":0.0482071607,"Steelix":3.4733538016,"Misdreavus":0.0,"Lapras":0.0,"Houndoom":0.0,"Jolteon":21.958033064,"Mew":23.6954177934,"Lugia":1.4421998541,"Nidoqueen":0.0,"Ho-Oh":0.0,"Suicune":0.0,"Umbreon":0.0482071607,"Celebi":0.0,"Arcanine":0.0,"Scizor":0.0,"Skarmory":0.0482071607,"Nidoking":0.0,"Meganium":0.0,"Venusaur":0.0,"Kingdra":0.0482071607,"Electrode":0.0,"Forretress":0.0},"usage":0.5078165,"Items":{"nevermeltice":0.0,"brightpowder":0.0,"mintberry":0.0,"leftovers":27.6730535178,"goldberry":0.0,"quickclaw":0.0,"miracleberry":0.4944420319,"kingsrock":0.0},"Raw count":657,"Spreads":{"Serious:252\/252\/252\/252\/252\/252":28.1674955496,"Serious:252\/0\/252\/252\/252\/252":0.0},"Happiness":{"255":28.1674955496},"Viability Ceiling":[52,90,90,60]},"Vaporeon":{"Moves":{"surf":1.7725748277,"bodyslam":0.0,"doubleedge":0.0,"blizzard":0.0,"shadowball":0.0,"batonpass":0.8270549388,"acidarmor":0.0,"rest":1.7725748277,"sandattack":0.0,"sleeptalk":0.945519889,"growth":1.7725748277,"frustration":0.0,"icebeam":0.0,"hydropump":0.0,"raindance":0.0,"substitute":0.0},"Checks and Counters":{},"Abilities":{"noability":1.7725748277},"Teammates":{"Cloyster":0.0,"Tyranitar":0.0,"Snorlax":1.7725748277,"Raikou":0.945519889,"Marowak":0.0,"Charizard":0.0,"Crobat":0.0,"Pikachu":0.0,"Jynx":0.0,"Mewtwo":1.7725748277,"Rhydon":0.0,"Mew":0.8270549388,"Exeggutor":0.0,"Blissey":0.0,"Girafarig":0.0,"Zapdos":0.8270549388,"Misdreavus":0.0,"Gengar":0.0,"Lugia":0.945519889,"Ho-Oh":0.0,"Umbreon":0.0,"Celebi":0.0,"Forretress":1.7725748277,"Scizor":0.0,"Skarmory":0.0,"Heracross":0.0,"Ledian":0.0,"Kingdra":0.0},"usage":0.0339626,"Items":{"leftovers":1.7725748277,"blackglasses":0.0,"mysticwater":0.0},"Raw count":52,"Spreads":{"Serious:252\/252\/252\/252\/252\/252":1.7725748277},"Happiness":{"0":0.0,"255":1.7725748277},"Viability Ceiling":[2,77,77,77]},"Tyranitar":{"Moves":{"rest":7.7046028452,"hiddenpowerbug":0.0,"firepunch":0.0,"hiddenpowerfighting":0.0,"icebeam":0.0,"thunderbolt":0.0,"curse":9.0912271837,"sleeptalk":0.0,"frustration":0.0,"hiddenpowergrass":0.0,"toxic":0.0,"flamethrower":2.2646011243,"surf":0.1767585202,"crunch":13.6017011427,"return":0.0,"rockslide":19.7687933869,"irontail":0.0,"outrage":0.0,"pursuit":4.2936348134,"fireblast":6.3839313899,"earthquake":2.0185640278,"hyperbeam":0.0,"dynamicpunch":1.8480590319,"protect":0.0,"roar":18.2147018453,"screech":0.0,"sandstorm":0.0,"thrash":0.0,"ancientpower":2.0971339212},"Checks and Counters":{},"Abilities":{"noability":21.8659273081},"Teammates":{"Quagsire":0.0,"Gengar":6.7278456759,"Golem":0.0,"Cloyster":9.0353296366,"Dragonite":0.0,"Gyarados":0.0,"Vaporeon":0.0,"Snorlax":17.9035971843,"Raikou":0.1873826241,"Muk":0.0,"Machamp":0.1873826241,"Marowak":0.0348388367,"Raichu":0.0,"Charizard":0.0,"Forretress":11.1881336273,"Miltank":0.0,"Scizor":0.0,"Mewtwo":20.410845888,"Mew":9.5150751006,"Exeggutor":0.0,"Sneasel":0.0,"Blissey":0.0,"Politoed":0.0,"Granbull":0.0,"Smeargle":0.0,"Sudowoodo":0.0,"Skarmory":0.0,"Starmie":0.0,"Heracross":0.0,"Steelix":2.2646011243,"Misdreavus":0.0348388367,"Lapras":0.0,"Houndoom":0.0,"Jolteon":6.6928285729,"Hitmontop":0.0,"Crobat":0.0,"Lugia":3.0657104797,"Aerodactyl":0.0,"Rapidash":0.0,"Wobbuffet":0.0,"Typhlosion":0.0,"Ho-Oh":0.4513809292,"Suicune":0.0,"Umbreon":0.0,"Celebi":2.7015693354,"Arcanine":0.0,"Togetic":0.0,"Alakazam":0.0,"empty":0.0,"Zapdos":11.0340100912,"Sunflora":0.0,"Venusaur":0.0,"Kingdra":2.7015693354,"Electrode":0.0,"Articuno":0.0,"Blastoise":0.0},"usage":0.3990532,"Items":{"mintberry":0.0,"goldberry":0.0,"leftovers":21.8659273081,"blackglasses":0.0,"quickclaw":0.0,"hardstone":0.0,"twistedspoon":0.0,"berserkgene":0.0,"energypowder":0.0,"nothing":0.0,"miracleberry":0.0,"kingsrock":0.0},"Raw count":737,"Spreads":{"Serious:252\/252\/252\/252\/252\/252":21.8659273081,"Serious:252\/252\/252\/252\/252\/4":0.0,"Serious:252\/252\/252\/252\/252\/244":0.0},"Happiness":{"0":0.0,"255":21.8659273081},"Viability Ceiling":[47,90,90,65]},"Snorlax":{"Moves":{"":0.0,"bubblebeam":0.0,"hiddenpowerdragon":0.0,"blizzard":0.0,"sweetkiss":0.0,"rest":31.6857257768,"firepunch":0.0,"hiddenpowerfighting":0.0,"icebeam":0.0,"hiddenpowerghost":0.0,"selfdestruct":5.3739909005,"substitute":0.0,"curse":47.3669764084,"thunder":0.0,"psychic":0.0,"sleeptalk":4.095784051,"amnesia":0.0,"frustration":0.0,"toxic":0.0,"swagger":0.0,"flamethrower":0.0,"surf":0.0,"return":6.6178190557,"rockslide":0.0,"shadowball":0.0039356387,"icepunch":0.0,"reflect":0.0,"bodyslam":5.155647686,"bellydrum":5.438273943,"fireblast":0.7268643419,"earthquake":18.6373996166,"hyperbeam":0.0,"protect":0.0,"snore":0.0,"metronome":0.127157363,"counter":0.0,"thunderbolt":0.0,"headbutt":0.0,"hiddenpowerflying":0.0,"lovelykiss":48.5178326751,"doubleedge":42.21784683,"seismictoss":0.0,"thunderpunch":0.0},"Checks and Counters":{},"Abilities":{"noability":53.9913135716},"Teammates":{"Golem":0.0,"Kingdra":0.0,"Jolteon":21.958033064,"Quagsire":0.0,"Cloyster":26.4557527884,"Dragonite":0.0,"Tauros":0.0,"Smeargle":0.0039356387,"Vaporeon":1.7725748277,"Slowking":0.0,"Tyranitar":17.9035971843,"Raikou":2.3151114487,"Hitmonlee":0.0,"Muk":0.0,"Poliwrath":0.0,"Machamp":0.0,"Marowak":0.529923891,"Scizor":0.0,"Lugia":11.5400134603,"Raichu":0.0,"Charizard":0.0039356387,"Ampharos":0.0,"Miltank":0.0,"Pikachu":0.0,"Jynx":0.0,"Shuckle":0.0,"Mewtwo":48.4878139494,"Rhydon":15.2652044911,"Mew":32.2309413334,"Exeggutor":0.0,"Jumpluff":0.0,"Skarmory":0.0,"Blissey":5.3877527594,"Gyarados":0.0,"empty":0.0,"Nidoking":0.0,"Forretress":18.4645078199,"Furret":0.0,"Nidorino":0.0,"Chansey":0.0,"Starmie":0.0,"Pidgeot":0.0,"Meganium":0.0,"Steelix":13.2928883927,"Lanturn":0.2190960727,"Lapras":0.0,"Espeon":0.0,"Houndoom":0.0223970889,"Gengar":8.6817772404,"Feraligatr":0.0,"Crobat":0.0,"Misdreavus":0.5741340403,"Aerodactyl":0.0,"Magneton":0.0,"Charmeleon":0.0,"Typhlosion":0.0,"Ho-Oh":1.0002971641,"Scyther":0.0,"Dodrio":0.0,"Suicune":0.0039356387,"Umbreon":0.5471832755,"Celebi":0.9748781859,"Arcanine":0.0,"Togetic":0.0,"Piloswine":0.0,"Alakazam":0.0,"Politoed":0.0,"Heracross":0.0,"Sunflora":0.0,"Venusaur":0.0,"Zapdos":17.1373940852,"Girafarig":0.0,"Blastoise":0.0},"usage":0.9379716,"Items":{"mintberry":0.2556678688,"leftovers":52.1931669777,"quickclaw":0.0,"berserkgene":0.0,"polkadotbow":0.0,"nothing":0.0,"miracleberry":1.5424787252},"Raw count":2005,"Spreads":{"Serious:252\/252\/252\/252\/252\/252":53.9913135716},"Happiness":{"0":0.0039356387,"255":53.987377933},"Viability Ceiling":[122,90,83,60]},"Raikou":{"Moves":{"":0.0,"hiddenpowerwater":0.0,"rest":2.8245187961,"hiddenpowerfire":0.0,"return":0.0,"detect":0.0,"hiddenpowerice":0.2603324581,"thunder":2.8245187961,"sleeptalk":2.564186338,"frustration":0.0,"hiddenpowergrass":0.0,"toxic":0.0,"quickattack":0.0,"crunch":2.1068707415,"thunderbolt":0.0,"reflect":0.0,"raindance":0.0,"thundershock":0.0,"hyperbeam":0.0,"irontail":0.0,"protect":0.0,"zapcannon":0.0,"roar":0.7176480546,"dig":0.0},"Checks and Counters":{},"Abilities":{"noability":2.8245187961},"Teammates":{"Golem":0.0,"Pinsir":0.0,"Cloyster":1.3695915597,"Corsola":0.0,"Vaporeon":0.945519889,"Tyranitar":0.1873826241,"Snorlax":2.3151114487,"Bayleef":0.0,"Muk":0.0,"Machamp":0.1873826241,"Marowak":0.0,"Porygon2":0.0,"Miltank":0.0,"Slowking":0.0,"Mewtwo":2.7628265308,"Rhydon":0.0,"Mew":0.6446982206,"Exeggutor":0.0,"Clefable":0.0,"Alakazam":0.0,"Blissey":0.2603324581,"Smeargle":0.0,"Aerodactyl":0.0,"Starmie":0.0,"Heracross":0.0,"Entei":0.0,"Steelix":1.3695915597,"Misdreavus":0.0,"Lapras":0.0,"Houndoom":0.0,"Gengar":0.0,"Feraligatr":0.0,"Lugia":2.3055109343,"Typhlosion":0.0,"Ho-Oh":0.2603324581,"Meganium":0.0,"Suicune":0.0,"Umbreon":0.0,"Celebi":0.0,"Forretress":1.2058523471,"Skarmory":0.0,"Donphan":0.0,"Zapdos":0.0,"Hitmontop":0.0,"Electrode":0.0,"Articuno":0.0,"Blastoise":0.0},"usage":0.0529358,"Items":{"nevermeltice":0.0,"mintberry":0.0,"leftovers":2.8245187961,"magnet":0.0,"nothing":0.0,"miracleberry":0.0,"kingsrock":0.0},"Raw count":306,"Spreads":{"Serious:252\/252\/252\/252\/252\/252":2.8245187961,"Serious:252\/252\/252\/252\/252\/216":0.0,"Serious:252\/0\/252\/252\/252\/252":0.0},"Happiness":{"0":0.0,"255":2.8245187961},"Viability Ceiling":[15,84,84,77]},"Machamp":{"Moves":{"dig":0.0,"thief":0.0,"rest":0.0,"firepunch":0.0,"hiddenpowerghost":0.0,"attract":0.0,"substitute":0.0,"curse":0.2490748893,"dynamicpunch":0.0,"lowkick":0.0,"crosschop":0.2490748893,"toxic":0.2490748893,"flamethrower":0.0,"endure":0.0,"return":0.0,"rockslide":0.2490748893,"icepunch":0.0,"fireblast":0.0,"detect":0.0,"seismictoss":0.0,"earthquake":0.0,"hyperbeam":0.0,"hiddenpowerbug":0.0,"protect":0.0,"lightscreen":0.0,"counter":0.0,"karatechop":0.0,"bodyslam":0.0,"thunderpunch":0.0,"doubleedge":0.0,"meditate":0.0,"encore":0.0},"Checks and Counters":{},"Abilities":{"noability":0.2490748893},"Teammates":{"Cloyster":0.0,"Dragonite":0.0,"Tyranitar":0.1873826241,"Snorlax":0.0,"Raikou":0.1873826241,"Articuno":0.0,"Marowak":0.0,"Zapdos":0.0,"Charizard":0.0,"Porygon2":0.0,"Arcanine":0.0,"Miltank":0.0,"Slowking":0.0,"Chansey":0.0,"Mewtwo":0.1873826241,"Rhydon":0.0,"Mew":0.1873826241,"Exeggutor":0.0,"Sneasel":0.0,"Politoed":0.0,"Girafarig":0.0,"Granbull":0.0,"Smeargle":0.0,"Aerodactyl":0.0,"Starmie":0.0,"Heracross":0.0,"Entei":0.0,"Steelix":0.0,"Misdreavus":0.0,"Alakazam":0.0,"Houndoom":0.0,"Gengar":0.0,"Venusaur":0.0,"Lugia":0.1873826241,"Rapidash":0.0,"Nidoqueen":0.0,"Magneton":0.0,"Typhlosion":0.0,"Ho-Oh":0.0,"Scyther":0.0,"Suicune":0.0,"Umbreon":0.0,"Celebi":0.0,"Ampharos":0.0,"Scizor":0.0,"Kingdra":0.0,"Skarmory":0.0,"empty":0.0,"Ledian":0.0,"Feraligatr":0.0,"Blastoise":0.0,"Pikachu":0.0,"Forretress":0.0},"usage":0.0035903,"Items":{"scopelens":0.0,"mintberry":0.0,"leftovers":0.2490748893,"goldberry":0.0,"quickclaw":0.0,"berserkgene":0.0,"blackbelt":0.0,"nothing":0.0,"brightpowder":0.0,"kingsrock":0.0},"Raw count":153,"Spreads":{"Serious:252\/252\/252\/252\/252\/252":0.2490748893},"Happiness":{"255":0.2490748893},"Viability Ceiling":[11,62,62,56]},"Marowak":{"Moves":{"hiddenpowerpoison":0.0,"rest":0.0,"firepunch":0.0,"hiddenpowerfighting":0.0,"ancientpower":0.0,"perishsong":0.0,"rockslide":0.5647627277,"swordsdance":0.5647627277,"frustration":0.0,"toxic":0.0,"flamethrower":0.0,"return":0.0,"dynamicpunch":0.0,"bodyslam":0.0,"bonemerang":0.0,"bellydrum":0.0,"fireblast":0.0,"earthquake":0.5647627277,"hiddenpowerbug":0.5647627277,"protect":0.0,"curse":0.0,"hiddenpowerflying":0.0,"doubleedge":0.0,"seismictoss":0.0,"thunderpunch":0.0},"Checks and Counters":{},"Abilities":{"noability":0.5647627277},"Teammates":{"Gengar":0.0,"Cloyster":0.529923891,"Gyarados":0.0,"Vaporeon":0.0,"Tyranitar":0.0348388367,"Snorlax":0.529923891,"Raikou":0.0,"Ursaring":0.0,"Muk":0.0,"Machamp":0.0,"Charizard":0.0,"Porygon2":0.0,"Crobat":0.0,"Pikachu":0.0,"Jynx":0.0,"Mewtwo":0.5647627277,"Mew":0.529923891,"Exeggutor":0.0,"Jumpluff":0.0,"Farfetch'd":0.0,"Clefable":0.0,"Alakazam":0.0,"Blissey":0.0,"Smeargle":0.0,"Ditto":0.0,"Chansey":0.0,"Starmie":0.0,"Tauros":0.0,"Heracross":0.0,"Steelix":0.0,"Misdreavus":0.0348388367,"Miltank":0.0,"Houndoom":0.0,"Jolteon":0.0,"Lugia":0.529923891,"Typhlosion":0.0,"Ho-Oh":0.0348388367,"Scyther":0.0,"Suicune":0.0,"Umbreon":0.0,"Celebi":0.0,"Forretress":0.0348388367,"Scizor":0.0,"Kingdra":0.0,"Skarmory":0.0,"Zapdos":0.0,"Feraligatr":0.0,"Ledian":0.0,"Blastoise":0.0},"usage":0.0108209,"Items":{"thickclub":0.5647627277},"Raw count":98,"Spreads":{"Serious:252\/252\/252\/252\/252\/252":0.5647627277,"Serious:252\/240\/252\/252\/252\/252":0.0},"Happiness":{"0":0.0,"255":0.5647627277},"Viability Ceiling":[9,67,67,61]},"Mewtwo":{"Moves":{"":0.0,"detect":0.0,"blizzard":0.2556678688,"rest":2.0345543724,"hiddenpowerpsychic":0.0,"return":0.0,"firepunch":0.0,"hiddenpowerfighting":5.3877527594,"icebeam":39.6751435293,"hiddenpowerghost":0.0,"thunderbolt":2.1976174753,"payday":0.0,"recover":21.3317258093,"substitute":1.9539315644,"curse":0.0,"hiddenpowerice":0.0,"hiddenpowergrass":0.0,"thunder":38.7645508108,"psychic":10.5677339541,"triattack":0.0,"hiddenpowerdark":0.0,"thunderwave":2.772320974,"amnesia":0.3280872028,"frustration":0.0,"confusion":0.0,"toxic":9.5526618771,"sleeptalk":2.0345543724,"flamethrower":37.3258219447,"selfdestruct":28.2771061887,"barrier":8.2642261654,"hiddenpowerbug":0.0,"shadowball":0.5160003269,"icepunch":0.0,"reflect":0.0,"solarbeam":0.0,"bodyslam":0.0,"fireblast":5.154557595,"swift":0.0,"hyperbeam":0.0,"metronome":0.0,"dynamicpunch":0.6148654182,"protect":0.0,"psychup":0.1721329235,"submission":1.7626079974,"futuresight":0.0,"psywave":0.0,"counter":0.2556678688,"disable":0.0,"doubleedge":0.0,"seismictoss":0.0,"nightmare":0.1721329235,"thunderpunch":0.0},"Checks and Counters":{},"Abilities":{"noability":54.8428554805},"Teammates":{"Golem":0.0,"Piloswine":0.0,"Moltres":0.0,"Quagsire":0.0,"Cloyster":26.4557527884,"Dragonite":0.0,"Tauros":0.0,"Nidoking":0.0,"Feraligatr":0.0,"Vaporeon":1.7725748277,"Tyranitar":20.410845888,"Snorlax":48.4878139494,"Raikou":2.7628265308,"Beedrill":0.0,"Hitmonlee":0.0,"Ursaring":0.0,"Muk":0.0,"Poliwrath":0.0,"Machamp":0.1873826241,"Marowak":0.5647627277,"Haunter":0.0,"Electabuzz":0.0,"Raichu":0.0,"Charizard":0.0,"Porygon2":0.0,"Arcanine":0.0,"Miltank":0.0,"Slowking":0.0,"Jynx":0.0,"Meganium":0.0,"Rhydon":15.2652044911,"Chansey":0.0,"Exeggutor":0.0,"Jumpluff":0.0,"Farfetch'd":0.0,"Skarmory":0.0,"Blissey":5.6480852175,"Politoed":0.0,"Girafarig":0.0,"Jolteon":21.958033064,"Smeargle":0.0,"Kingdra":2.7015693354,"Ditto":0.0,"Aerodactyl":0.0,"Starmie":0.0,"Pidgeot":0.0,"Heracross":0.0,"Entei":0.0,"empty":0.0,"Lanturn":0.2190960727,"Lapras":0.0,"Espeon":0.0,"Houndoom":0.0223970889,"Gengar":8.6817772404,"Mew":31.9515220111,"Crobat":0.0,"Steelix":12.8300220849,"Misdreavus":0.6089728771,"Lugia":14.6429736626,"Articuno":0.0,"Magneton":0.0,"Dugtrio":0.0,"Typhlosion":0.0,"Ho-Oh":0.8789263664,"Scyther":0.0,"Suicune":0.0,"Umbreon":0.5471832755,"Celebi":3.6261876674,"Ampharos":0.0,"Scizor":0.0,"Persian":0.0,"Alakazam":0.0,"Donphan":0.0,"Zapdos":16.7208519927,"Venusaur":0.0,"Blastoise":0.0,"Electrode":0.0,"Pikachu":0.0,"Forretress":21.4149242349},"usage":0.9900355,"Items":{"scopelens":0.0,"brightpowder":0.0,"mintberry":0.0,"leftovers":53.949648925,"goldberry":0.0,"przcureberry":0.0,"magnet":0.0,"twistedspoon":0.0,"berserkgene":0.0,"blackbelt":0.0,"nothing":0.0,"miracleberry":0.8932065555,"psncureberry":0.0,"sunstone":0.0,"kingsrock":0.0,"pinkbow":0.0},"Raw count":2141,"Spreads":{"Serious:252\/252\/252\/252\/252\/252":54.8428554805,"Serious:252\/0\/252\/252\/252\/252":0.0},"Happiness":{"0":0.0,"255":54.8428554805},"Viability Ceiling":[149,90,84,59]},"Rhydon":{"Moves":{"blizzard":0.0,"rest":0.0,"firepunch":0.0,"hiddenpowerfighting":0.0,"icebeam":0.0,"curse":16.6624802796,"thunder":0.0,"sleeptalk":0.0,"frustration":0.0,"toxic":0.0,"flamethrower":0.0,"surf":0.0,"crunch":0.0,"rockslide":16.6624802796,"bodyslam":0.0,"fireblast":0.0,"earthquake":16.6624802796,"hyperbeam":0.0,"hiddenpowerbug":0.0,"protect":0.0,"submission":0.0,"zapcannon":0.0,"roar":16.6624802796,"counter":0.0,"seismictoss":0.0,"hiddenpowerrock":0.0,"thunderpunch":0.0},"Checks and Counters":{},"Abilities":{"noability":16.6624802796},"Teammates":{"Jolteon":15.2652044911,"Cloyster":15.2652044911,"Dragonite":0.0,"Beedrill":0.0,"Vaporeon":0.0,"Snorlax":15.2652044911,"Raikou":0.0,"Kangaskhan":0.0,"Machamp":0.0,"Raichu":0.0,"Charizard":0.0,"Porygon2":0.0,"Miltank":0.0,"Pikachu":0.0,"Jynx":0.0,"Mewtwo":15.2652044911,"Mew":15.2652044911,"Blissey":0.0,"Aerodactyl":0.0,"Pidgeot":0.0,"Heracross":0.0,"Entei":0.0,"Steelix":0.0,"Lapras":0.0,"Houndoom":0.0,"Gengar":0.0,"Lugia":0.0,"Typhlosion":0.0,"Ho-Oh":0.0,"Scyther":0.0,"Dodrio":0.0,"Umbreon":0.0,"Celebi":0.0,"Forretress":0.0,"Skarmory":0.0,"Nidoking":0.0,"Zapdos":0.0,"Feraligatr":0.0,"Kingler":0.0},"usage":0.2924817,"Items":{"scopelens":0.0,"leftovers":16.6624802796,"hardstone":0.0,"softsand":0.0,"nothing":0.0,"mysteryberry":0.0,"pinkbow":0.0},"Raw count":73,"Spreads":{"Serious:252\/252\/252\/252\/252\/252":16.6624802796},"Happiness":{"0":0.0,"255":16.6624802796},"Viability Ceiling":[3,74,74,74]},"Mew":{"Moves":{"sludgebomb":0.0,"":0.0,"dynamicpunch":0.0,"flash":0.0,"detect":0.2556678688,"blizzard":0.0,"softboiled":4.0874850472,"thief":0.0,"rest":0.0,"mudslap":0.0223970889,"return":0.0,"firepunch":0.0,"hiddenpowerfighting":0.0,"icebeam":0.0,"selfdestruct":0.0,"dragonbreath":0.0,"substitute":0.0,"hiddenpowerdark":0.0,"curse":0.0,"hiddenpowerpsychic":0.0,"gigadrain":0.0,"thunder":0.0,"psychic":0.5693145202,"cut":0.0,"transform":0.0,"frustration":0.2556678688,"swordsdance":35.9428192565,"thunderwave":19.4408484804,"dreameater":0.0,"toxic":0.0,"sleeptalk":0.0,"flamethrower":0.0,"surf":0.0,"explosion":30.0095732684,"triattack":0.0,"rockslide":12.4227767355,"shadowball":6.1762444575,"icepunch":0.0,"reflect":0.0,"megakick":0.0,"bodyslam":0.7855917597,"eggbomb":0.0,"fireblast":16.6624802796,"psywave":0.0,"earthquake":12.1738850884,"hyperbeam":0.0,"metronome":0.0223970889,"fly":0.0,"hiddenpowerbug":0.0,"protect":0.0,"swagger":0.0,"snore":0.0,"psychup":0.0,"submission":5.5997392241,"roar":0.0,"counter":0.3069129891,"thunderbolt":0.0,"waterfall":0.0,"hiddenpowerflying":0.0,"thunderpunch":0.0,"doubleedge":0.0,"seismictoss":0.0,"hiddenpowerrock":0.0,"megadrain":0.0,"ancientpower":0.1497358346,"whirlwind":0.0},"Checks and Counters":{},"Abilities":{"noability":36.2208842142},"Teammates":{"Golem":0.0,"Pinsir":0.0,"Jolteon":21.958033064,"Quagsire":0.0,"Cloyster":23.6954177934,"Dragonite":0.0,"Tauros":0.0,"Vaporeon":0.8270549388,"Golbat":0.0,"Tyranitar":9.5150751006,"Snorlax":32.2309413334,"Raikou":0.6446982206,"Hitmonlee":0.0,"Ursaring":0.0,"Muk":0.0,"Forretress":4.8292554553,"Machamp":0.1873826241,"Marowak":0.529923891,"Lugia":4.4818474729,"Charizard":0.0039356387,"Porygon2":0.0,"Ampharos":0.0,"Miltank":0.0,"Pikachu":0.0,"Jynx":0.0,"Mewtwo":31.9515220111,"Rhydon":15.2652044911,"Chansey":0.0,"Exeggutor":0.0,"Jumpluff":0.0,"Skarmory":0.0,"Nidoqueen":0.0,"Blissey":0.0,"empty":0.0,"Girafarig":0.0,"Smeargle":0.0039356387,"Aerodactyl":0.0,"Starmie":0.0,"Pidgeot":0.0,"Meganium":0.0,"Entei":0.0,"Tentacruel":0.0,"Lanturn":0.2190960727,"Espeon":0.0,"Houndoom":0.0223970889,"Gengar":1.9539315644,"Steelix":4.2425793952,"Misdreavus":0.0,"Raticate":0.0,"Ho-Oh":0.6722099613,"Suicune":0.0039356387,"Umbreon":0.2190960727,"Celebi":0.0726569428,"Arcanine":0.0,"Scizor":0.0,"Heracross":0.0,"Alakazam":0.0,"Nidoking":0.0,"Zapdos":8.5614893775,"Venusaur":0.0,"Kingdra":0.0,"Electrode":0.0,"Blastoise":0.0},"usage":0.6211358,"Items":{"brightpowder":0.0,"leftovers":19.5584039345,"goldberry":0.0,"quickclaw":0.0,"przcureberry":0.0,"twistedspoon":0.0,"berserkgene":0.0,"nothing":0.0,"miracleberry":16.6624802796,"kingsrock":0.0},"Raw count":1620,"Spreads":{"Serious:236\/252\/252\/252\/252\/252":0.0,"Serious:252\/252\/252\/252\/252\/252":36.2208842142,"Serious:252\/0\/252\/252\/252\/252":0.0},"Happiness":{"0":0.2556678688,"255":35.9652163454},"Viability Ceiling":[108,90,80,60]},"Blissey":{"Moves":{"":0.0,"blizzard":0.0,"softboiled":5.7897731214,"rest":0.0,"hiddenpowerflying":0.0,"icebeam":0.0,"return":0.0,"attract":0.0,"substitute":0.0,"teleport":0.0,"lightscreen":0.0,"triattack":0.0,"thunder":0.0,"psychic":0.0,"flash":0.0,"sleeptalk":0.0,"hiddenpowerdark":0.0,"thunderwave":0.0,"healbell":5.7897731214,"dreameater":0.0,"hiddenpowergrass":0.0,"toxic":5.7897731214,"flamethrower":5.7897731214,"icywind":0.0,"thunderbolt":0.0,"frustration":0.0,"shadowball":0.0,"reflect":0.0,"watergun":0.0,"fireblast":0.0,"curse":0.0,"eggbomb":0.0,"sing":0.0,"seismictoss":0.0,"hiddenpowerbug":0.0,"protect":0.0,"metronome":0.0,"zapcannon":0.0,"counter":0.0,"raindance":0.0,"bodyslam":0.0,"doubleedge":0.0,"defensecurl":0.0},"Checks and Counters":{},"Abilities":{"noability":5.7897731214},"Teammates":{"Golem":0.0,"Jolteon":0.0,"Quagsire":0.0,"Cloyster":0.0,"Dragonite":0.0,"Gyarados":0.0,"Vaporeon":0.0,"Tyranitar":0.0,"Snorlax":5.3877527594,"Raikou":0.2603324581,"Hitmonlee":0.0,"Muk":0.0,"Marowak":0.0,"Haunter":0.0,"Charizard":0.0,"Porygon2":0.0,"Miltank":0.0,"Pikachu":0.0,"Jynx":0.0,"Shuckle":0.0,"Mewtwo":5.6480852175,"Rhydon":0.0,"Tentacruel":0.0,"Mew":0.0,"Exeggutor":0.0,"Jumpluff":0.0,"Clefable":0.0,"Nidoking":0.0,"Smeargle":0.0,"Ditto":0.0,"Starmie":0.0,"Meganium":0.0,"Steelix":5.3877527594,"Misdreavus":0.0,"Lapras":0.0,"Houndoom":0.0,"Gengar":0.0,"Crobat":0.0,"Lugia":5.6480852175,"Heracross":0.0,"Golduck":0.0,"Typhlosion":0.0,"Ho-Oh":0.2603324581,"Suicune":0.0,"Umbreon":0.0,"Celebi":0.0,"Forretress":5.6480852175,"Scizor":0.0,"Kingdra":0.0,"Skarmory":0.0,"Donphan":0.0,"Zapdos":0.0,"Venusaur":0.0,"Girafarig":0.0,"Electrode":0.0,"Articuno":0.0,"Golbat":0.0},"usage":0.1082174,"Items":{"mintberry":0.0,"scopelens":0.0,"leftovers":5.7897731214,"goldberry":0.0,"quickclaw":0.0,"berserkgene":0.0,"nothing":0.0,"kingsrock":0.0},"Raw count":201,"Spreads":{"Serious:252\/252\/252\/252\/252\/252":5.7897731214,"Serious:252\/0\/252\/252\/252\/252":0.0},"Happiness":{"0":0.0,"255":5.7897731214},"Viability Ceiling":[22,73,73,56]},"Misdreavus":{"Moves":{"hiddenpowerbug":0.0,"protect":0.0,"curse":0.0,"thunderbolt":0.0,"hiddenpowerfighting":0.0,"spite":0.0,"shadowball":0.0,"perishsong":0.1416879039,"thief":0.9280453922,"rest":0.0,"hiddenpowerfire":0.0,"meanlook":0.0,"thunder":0.8932065555,"toxic":0.7863574883,"painsplit":0.9280453922,"destinybond":0.0,"confuseray":0.0348388367,"psychic":0.0},"Checks and Counters":{},"Abilities":{"noability":0.9280453922},"Teammates":{"Cloyster":0.0,"Vaporeon":0.0,"Tyranitar":0.0348388367,"Snorlax":0.5741340403,"Dragonair":0.0,"Machamp":0.0,"Marowak":0.0348388367,"Raichu":0.0,"Miltank":0.0,"Slowking":0.0,"Shuckle":0.0,"Mewtwo":0.6089728771,"Mew":0.0,"Jumpluff":0.0,"Skarmory":0.0,"Blissey":0.0,"Smeargle":0.0,"Steelix":0.5741340403,"Houndoom":0.0,"Jolteon":0.0,"Lugia":0.0,"Ho-Oh":0.0348388367,"Suicune":0.0,"Celebi":0.5741340403,"Forretress":0.6089728771,"Persian":0.0,"Sneasel":0.0,"Zapdos":0.0,"Pikachu":0.0,"Raikou":0.0},"usage":0.0116679,"Items":{"nothing":0.9280453922,"leftovers":0.0,"quickclaw":0.0,"scopelens":0.0},"Raw count":80,"Spreads":{"Serious:252\/252\/252\/252\/252\/252":0.9280453922,"Serious:252\/0\/252\/252\/252\/252":0.0},"Happiness":{"255":0.9280453922},"Viability Ceiling":[7,59,59,54]},"Entei":{"Moves":{"protect":0.0,"strength":0.0,"firespin":0.0,"sunnyday":0.0482071607,"roar":0.0,"return":0.0,"hiddenpowerdark":0.0,"solarbeam":0.0482071607,"hiddenpowerfire":0.0,"hyperbeam":0.0,"hiddenpowerfighting":0.0482071607,"hiddenpowergrass":0.0,"leer":0.0,"fireblast":0.0482071607,"flamethrower":0.0,"psychup":0.0},"Checks and Counters":{},"Abilities":{"noability":0.0482071607},"Teammates":{"Moltres":0.0,"Cloyster":0.0482071607,"Raikou":0.0,"Machamp":0.0,"Charizard":0.0,"Mewtwo":0.0,"Rhydon":0.0,"Mew":0.0,"Girafarig":0.0,"Meganium":0.0,"Houndoom":0.0,"Gengar":0.0482071607,"Lugia":0.0,"Typhlosion":0.0,"Ho-Oh":0.0,"Suicune":0.0,"Umbreon":0.0482071607,"Celebi":0.0,"Arcanine":0.0,"Skarmory":0.0482071607,"Heracross":0.0,"Kingdra":0.0482071607},"usage":0.0009237,"Items":{"leftovers":0.0482071607,"firestone":0.0,"psncureberry":0.0,"charcoal":0.0},"Raw count":13,"Spreads":{"Serious:252\/252\/252\/252\/252\/252":0.0482071607},"Happiness":{"255":0.0482071607},"Viability Ceiling":[2,45,45,45]},"Steelix":{"Moves":{"hiddenpowersteel":0.0,"rest":5.3877527594,"hiddenpowerelectric":0.0,"hiddenpowerfire":0.0,"hiddenpowerfighting":0.0,"dragonbreath":0.0,"substitute":0.0,"curse":9.4974158953,"sleeptalk":5.3877527594,"toxic":0.0,"crunch":0.0,"explosion":9.4974158953,"rockslide":0.1575498216,"irontail":4.2000903241,"hiddenpowerflying":0.0,"earthquake":10.6850783305,"hiddenpowerbug":0.0,"roar":14.727618833,"bind":0.0,"bodyslam":0.0,"doubleedge":0.0,"hiddenpowerrock":0.0},"Checks and Counters":{},"Abilities":{"noability":14.8851686546},"Teammates":{"Golem":0.0,"Jolteon":0.0,"Cloyster":3.4733538016,"Gyarados":0.0,"Tyranitar":2.2646011243,"Snorlax":13.2928883927,"Raikou":1.3695915597,"Muk":0.0,"Machamp":0.0,"Marowak":0.0,"Forretress":6.008211015,"Miltank":0.0,"Mewtwo":12.8300220849,"Rhydon":0.0,"Mew":4.2425793952,"Exeggutor":0.0,"Jumpluff":0.0,"Clefable":0.0,"Blissey":5.3877527594,"empty":0.0,"Girafarig":0.0,"Smeargle":0.0,"Starmie":0.0,"Zapdos":5.5869986152,"Misdreavus":0.5741340403,"Houndoom":0.0,"Gengar":0.0,"Venusaur":0.0,"Lugia":9.4130472186,"Heracross":0.0,"Typhlosion":0.0,"Ho-Oh":0.7446292953,"Scyther":0.0,"Suicune":0.0,"Umbreon":0.3280872028,"Celebi":0.9485454584,"Ampharos":0.0,"Scizor":0.0,"Piloswine":0.0,"Nidoking":0.0,"Meganium":0.0,"Feraligatr":0.0,"Kingdra":0.0,"Blastoise":0.0},"usage":0.2546921,"Items":{"mintberry":0.0,"blackglasses":0.0,"metalcoat":0.0,"brightpowder":0.0,"leftovers":14.8851686546,"goldberry":0.0,"quickclaw":0.0,"berserkgene":0.0,"softsand":0.0,"nothing":0.0,"miracleberry":0.0},"Raw count":561,"Spreads":{"Serious:252\/252\/252\/252\/252\/252":10.1164316596,"Serious:252\/252\/252\/0\/0\/252":0.0,"Serious:252\/252\/252\/252\/252\/0":4.768736995},"Happiness":{"255":14.8851686546},"Viability Ceiling":[41,79,79,64]},"Lanturn":{"Moves":{"surf":0.2190960727,"confuseray":0.2190960727,"thunderbolt":0.0,"thunder":0.2190960727,"thunderwave":0.2190960727,"lightscreen":0.0,"attract":0.0},"Checks and Counters":{},"Abilities":{"noability":0.2190960727},"Teammates":{"Lugia":0.2190960727,"Umbreon":0.2190960727,"Forretress":0.0,"Mew":0.2190960727,"Snorlax":0.2190960727,"Houndoom":0.0,"Bellossom":0.0,"Mewtwo":0.2190960727,"Muk":0.0},"usage":0.0041979,"Items":{"magnet":0.0,"leftovers":0.2190960727},"Raw count":6,"Spreads":{"Serious:252\/252\/252\/252\/252\/252":0.2190960727},"Happiness":{"255":0.2190960727},"Viability Ceiling":[1,57,57,57]},"Houndoom":{"Moves":{"crunch":0.1721329235,"protect":0.0,"hiddenpowerrock":0.0,"curse":0.0,"sunnyday":0.0,"roar":0.0,"shadowball":0.0,"counter":0.0,"mudslap":0.0,"hiddenpowerdark":0.0,"hiddenpowerelectric":0.0,"solarbeam":0.0,"pursuit":0.1721329235,"hiddenpowerfighting":0.0,"hiddenpowergrass":0.0,"toxic":0.0,"fireblast":0.1721329235,"flamethrower":0.1721329235},"Checks and Counters":{},"Abilities":{"noability":0.1721329235},"Teammates":{"Golem":0.0,"Moltres":0.0,"Cloyster":0.0,"Tauros":0.0,"Tyranitar":0.0,"Snorlax":0.0223970889,"Raikou":0.0,"Hitmonlee":0.0,"Ursaring":0.0,"Xatu":0.0,"Muk":0.0,"Machamp":0.0,"Marowak":0.0,"Electabuzz":0.0,"Charizard":0.0,"Porygon2":0.0,"Aipom":0.0,"Crobat":0.0,"Chansey":0.0,"Mewtwo":0.0223970889,"Rhydon":0.0,"Mew":0.0223970889,"Exeggutor":0.0,"Blastoise":0.0,"Bellossom":0.0,"Blissey":0.0,"empty":0.0,"Donphan":0.0,"Smeargle":0.0,"Aerodactyl":0.0,"Starmie":0.0,"Heracross":0.0,"Entei":0.0,"Steelix":0.0,"Misdreavus":0.0,"Miltank":0.0,"Ariados":0.0,"Gengar":0.0,"Lanturn":0.0,"Lugia":0.0,"Nidoqueen":0.0,"Typhlosion":0.0,"Ho-Oh":0.0,"Celebi":0.0223970889,"Suicune":0.0,"Wooper":0.0,"Arcanine":0.0,"Scizor":0.0,"Kingdra":0.0,"Skarmory":0.0,"Nidoking":0.0,"Meganium":0.0,"Venusaur":0.0,"Zapdos":0.0,"Forretress":0.0223970889},"usage":0.0004291,"Items":{"charcoal":0.0,"brightpowder":0.0,"leftovers":0.0,"blackglasses":0.0,"hardstone":0.0,"nothing":0.0,"miracleberry":0.1721329235},"Raw count":73,"Spreads":{"Serious:252\/252\/252\/252\/252\/252":0.1721329235,"Serious:252\/0\/252\/252\/252\/252":0.0},"Happiness":{"255":0.1721329235},"Viability Ceiling":[8,55,55,54]},"Gengar":{"Moves":{"":0.0,"hiddenpowerpoison":0.0,"psychic":0.0482071607,"thief":9.6585344096,"rest":0.0,"return":0.0,"firepunch":0.0,"hiddenpowerfighting":0.0,"thunderbolt":0.0482071607,"attract":0.0,"substitute":0.0,"curse":0.0,"gigadrain":0.0,"thunder":0.2661699189,"perishsong":0.0,"hiddenpowerdark":0.0,"haze":0.0,"dreameater":0.0,"hiddenpowergrass":0.0,"toxic":0.0,"destinybond":0.0,"confuseray":0.0,"explosion":9.9729114892,"doubleedge":0.0,"nightshade":0.0,"shadowball":0.0,"icepunch":9.9729114892,"bodyslam":0.0,"seismictoss":0.0,"psywave":0.0,"hyperbeam":0.0,"metronome":0.0,"dynamicpunch":7.9707727641,"protect":0.0,"psychup":0.0,"submission":0.0,"megadrain":0.0,"hypnosis":1.9539315644,"hiddenpowerflying":0.0,"endure":0.0,"meanlook":0.0,"nightmare":0.0,"thunderpunch":0.0},"Checks and Counters":{},"Abilities":{"noability":9.9729114892},"Teammates":{"Golem":0.0,"Kingdra":0.0482071607,"Moltres":0.0,"Cloyster":0.0482071607,"Dragonite":0.0,"Tauros":0.0,"Suicune":0.0,"Vaporeon":0.0,"Tyranitar":6.7278456759,"Snorlax":8.6817772404,"Raikou":0.0,"Hitmonlee":0.0,"Feraligatr":0.0,"Muk":0.0,"Poliwrath":0.0,"Machamp":0.0,"Marowak":0.0,"Raichu":0.0,"Charizard":0.0,"Porygon2":0.0,"Ampharos":0.0,"Miltank":0.0,"Pikachu":0.0,"Jynx":0.0,"Mewtwo":8.6817772404,"Rhydon":0.0,"Chansey":0.0,"Exeggutor":0.0,"Skarmory":0.0482071607,"Blissey":0.0,"Gyarados":0.0,"empty":0.0,"Smeargle":0.0,"Aerodactyl":0.0,"Starmie":0.0,"Pidgeot":0.0,"Meganium":0.0,"Entei":0.0482071607,"Steelix":0.0,"Lapras":0.0,"Houndoom":0.0,"Jolteon":0.0,"Mew":1.9539315644,"Crobat":0.0,"Lugia":0.0,"Rapidash":0.0,"Nidoqueen":0.0,"Typhlosion":0.0,"Ho-Oh":0.0,"Dodrio":0.0,"Slowbro":0.0,"Sandslash":0.0,"Umbreon":0.0482071607,"Celebi":0.0,"Arcanine":0.0,"Scizor":0.0,"Heracross":0.0,"Alakazam":0.0,"Nidoking":0.0,"Zapdos":8.6817772404,"Venusaur":0.0,"Blastoise":0.0,"Slowking":0.0,"Kingler":0.0,"Forretress":8.6817772404},"usage":0.1672667,"Items":{"charcoal":0.0,"blackglasses":0.0,"leftovers":0.3143770796,"luckypunch":0.0,"goldberry":0.0,"quickclaw":0.0,"magnet":0.0,"twistedspoon":0.0,"berserkgene":0.0,"spelltag":0.0,"nothing":9.6585344096,"brightpowder":0.0,"kingsrock":0.0},"Raw count":315,"Spreads":{"Serious:252\/252\/252\/252\/252\/252":9.9729114892,"Serious:252\/0\/252\/252\/252\/252":0.0},"Happiness":{"255":9.9729114892},"Viability Ceiling":[24,83,83,64]},"Lugia":{"Moves":{"":0.0,"detect":0.0,"blizzard":0.2556678688,"rest":0.9303953515,"hiddenpowerfire":0.0,"hiddenpowerfighting":0.0,"icebeam":0.2556678688,"return":0.0,"recover":14.5719647508,"dragonbreath":0.0,"curse":15.5023601023,"gigadrain":0.0,"thunder":0.0,"psychic":0.0,"sleeptalk":0.0,"frustration":0.0,"steelwing":0.0,"toxic":0.0,"surf":0.0,"aeroblast":15.5023601023,"thunderbolt":0.0,"dreameater":0.0,"shadowball":0.0,"irontail":0.0,"raindance":0.0,"hiddenpowerflying":0.0,"hydropump":0.0,"ancientpower":0.2556678688,"earthquake":7.7341252436,"hyperbeam":0.0,"fly":0.0,"hiddenpowerbug":0.0,"protect":0.2556678688,"zapcannon":0.0,"roar":0.0,"gust":0.0,"safeguard":0.0,"futuresight":0.0,"waterfall":0.0,"hiddenpowerrock":0.0,"whirlwind":7.7682348587},"Checks and Counters":{},"Abilities":{"noability":15.758027971},"Teammates":{"Golem":0.0,"Pinsir":0.0,"Kingdra":2.7015693354,"Moltres":0.0,"Quagsire":0.0,"Cloyster":1.4421998541,"Dragonite":0.0,"Corsola":0.0,"Nidoking":0.0,"Jynx":0.0,"Vaporeon":0.945519889,"Tyranitar":3.0657104797,"Snorlax":11.5400134603,"Raikou":2.3055109343,"Bayleef":0.0,"Ursaring":0.0,"Muk":0.0,"Machamp":0.1873826241,"Marowak":0.529923891,"Charizard":0.0,"Porygon2":0.0,"Arcanine":0.0,"Miltank":0.0,"Pikachu":0.0,"Gengar":0.0,"Mew":4.4818474729,"Mewtwo":14.6429736626,"Rhydon":0.0,"Suicune":0.0,"Chansey":0.0,"Exeggutor":0.0,"Jumpluff":0.0,"Pidgeot":0.0,"Clefable":0.0,"Bellossom":0.0,"Feraligatr":0.0,"Blissey":5.6480852175,"empty":0.0,"Girafarig":0.0,"Granbull":0.0,"Smeargle":0.0,"Aerodactyl":0.0,"Skarmory":0.0,"Starmie":0.0,"Gyarados":0.0,"Heracross":0.0,"Entei":0.0,"Steelix":9.4130472186,"Misdreavus":0.0,"Lapras":0.0,"Espeon":0.0,"Houndoom":0.0,"Jolteon":0.0,"Venusaur":0.0,"Crobat":0.0,"Lanturn":0.2190960727,"Wobbuffet":0.0,"Articuno":0.0,"Nidoqueen":0.0,"Magneton":0.0,"Typhlosion":0.0,"Ho-Oh":0.5160003269,"Scyther":0.0,"Meganium":0.0,"Slowbro":0.0,"Umbreon":0.2190960727,"Celebi":2.7478935506,"Ampharos":0.0,"Scizor":0.0,"Piloswine":0.0,"Alakazam":0.0,"Donphan":0.0,"Zapdos":3.0666942809,"Hitmontop":0.0,"Ledian":0.0,"Electrode":0.0,"Slowking":0.0,"Forretress":9.7739250461},"usage":0.2814473,"Items":{"scopelens":0.0,"blackglasses":0.0,"mintberry":0.0,"leftovers":15.758027971,"goldberry":0.0,"quickclaw":0.0,"twistedspoon":0.0,"berserkgene":0.0,"mysticwater":0.0,"berry":0.0,"brightpowder":0.0,"nothing":0.0,"miracleberry":0.0,"sharpbeak":0.0},"Raw count":1250,"Spreads":{"Serious:252\/252\/252\/252\/252\/252":15.758027971},"Happiness":{"0":0.0,"255":15.758027971},"Viability Ceiling":[96,84,84,58]},"Ho-Oh":{"Moves":{"":0.0,"sacredfire":1.0398005901,"hiddenpowerwater":0.0,"rest":0.0,"hiddenpowerelectric":0.0,"hiddenpowerfire":0.0,"hiddenpowerfighting":0.0,"return":0.4165420925,"recover":1.0398005901,"curse":0.4165420925,"hiddenpowerice":0.0,"gigadrain":0.0,"thunder":0.0,"psychic":0.0,"hiddenpowerdark":0.0,"sleeptalk":0.0,"frustration":0.0,"steelwing":0.0,"toxic":0.0,"flamethrower":0.2556678688,"thunderbolt":0.2951712948,"shadowball":0.0,"hiddenpowergrass":0.0,"fireblast":0.0,"hiddenpowerflying":0.0,"detect":0.2556678688,"ancientpower":0.2556678688,"earthquake":0.8789263664,"hyperbeam":0.0,"fly":0.0,"protect":0.0,"sunnyday":0.0,"futuresight":0.0,"roar":0.0,"gust":0.0,"safeguard":0.0,"solarbeam":0.0,"whirlwind":0.3280872028},"Checks and Counters":{},"Abilities":{"noability":1.2954684589},"Teammates":{"Golem":0.0,"Pinsir":0.0,"Moltres":0.0,"Quagsire":0.0,"Cloyster":0.0,"Dragonite":0.0,"Tauros":0.0,"Suicune":0.0,"Vaporeon":0.0,"Tyranitar":0.4513809292,"Snorlax":1.0002971641,"Raikou":0.2603324581,"Kangaskhan":0.0,"Hitmonlee":0.0,"Nidoking":0.0,"Heracross":0.0,"Machamp":0.0,"Marowak":0.0348388367,"Haunter":0.0,"Raichu":0.0,"Charizard":0.0,"Porygon2":0.0,"Arcanine":0.0,"Miltank":0.0,"Slowking":0.0,"Jynx":0.0,"Mewtwo":0.8789263664,"Rhydon":0.0,"Mew":0.6722099613,"Exeggutor":0.0,"Alakazam":0.0,"Nidoqueen":0.0,"Blissey":0.2603324581,"empty":0.0,"Girafarig":0.0,"Granbull":0.0,"Smeargle":0.0,"Ditto":0.0,"Aerodactyl":0.0,"Skarmory":0.0,"Starmie":0.0,"Pidgeot":0.0,"Meganium":0.0,"Entei":0.0,"Steelix":0.7446292953,"Misdreavus":0.0348388367,"Lapras":0.0,"Houndoom":0.0,"Jolteon":0.0,"Venusaur":0.0,"Crobat":0.0,"Lugia":0.5160003269,"Articuno":0.0,"Gengar":0.0,"Typhlosion":0.0,"Slowbro":0.0,"Sandslash":0.0,"Umbreon":0.3280872028,"Celebi":0.3280872028,"Ampharos":0.0,"Scizor":0.0,"Piloswine":0.0,"Sneasel":0.0,"Donphan":0.0,"Zapdos":0.4165420925,"Feraligatr":0.0,"Kingdra":0.0,"Electrode":0.0,"Pikachu":0.0,"Forretress":0.5508391636},"usage":0.0248212,"Items":{"charcoal":0.2556678688,"firestone":0.0,"miracleberry":0.0,"goldberry":0.0,"mintberry":0.0,"leftovers":1.0398005901,"blackglasses":0.0,"quickclaw":0.0,"hardstone":0.0,"berserkgene":0.0,"nothing":0.0,"mysteryberry":0.0,"brightpowder":0.0,"fastball":0.0,"sharpbeak":0.0},"Raw count":688,"Spreads":{"Serious:252\/252\/252\/252\/252\/252":1.2954684589,"Serious:252\/252\/252\/252\/252\/248":0.0,"Serious:252\/0\/252\/252\/252\/252":0.0},"Happiness":{"0":0.0,"255":1.2954684589},"Viability Ceiling":[67,84,84,55]},"Umbreon":{"Moves":{"":0.1570820266,"rest":0.0,"growth":0.0,"feintattack":0.0,"substitute":0.0,"growl":0.0,"detect":0.0,"psychic":0.0,"batonpass":1.1396548011,"hiddenpowerdark":0.3280872028,"sleeptalk":0.0,"toxic":0.3762943635,"confuseray":1.1396548011,"quickattack":0.0,"return":0.0,"doubleedge":0.0,"hiddenpowerbug":0.0,"shadowball":0.0,"reflect":0.3280872028,"curse":0.0,"charm":0.0482071607,"pursuit":0.0482071607,"irontail":0.0,"protect":0.0,"psychup":0.0,"moonlight":1.2968530919,"bodyslam":0.0620140461,"meanlook":1.1396548011,"skullbash":0.0,"bite":0.0},"Checks and Counters":{},"Abilities":{"noability":1.5159491646},"Teammates":{"Quagsire":0.0,"Gengar":0.0482071607,"Golem":0.0,"Cloyster":0.0482071607,"Dragonite":0.0,"Vaporeon":0.0,"Tyranitar":0.0,"Snorlax":0.5471832755,"Raikou":0.0,"Ursaring":0.0,"Machamp":0.0,"Marowak":0.0,"Charizard":0.0,"Forretress":0.0,"Crobat":0.0,"Shuckle":0.0,"Mewtwo":0.5471832755,"Rhydon":0.0,"Mew":0.2190960727,"Exeggutor":0.0,"Skarmory":0.0482071607,"Blissey":0.0,"Girafarig":0.0,"Smeargle":0.0,"Ditto":0.0,"Aerodactyl":0.0,"Starmie":0.0,"Pidgeot":0.0,"Heracross":0.0,"Entei":0.0482071607,"Steelix":0.3280872028,"Lanturn":0.2190960727,"Miltank":0.0,"Jolteon":0.0,"Feraligatr":0.0,"Lugia":0.2190960727,"Magneton":0.0,"Typhlosion":0.0,"Ho-Oh":0.3280872028,"Scyther":0.0,"Suicune":0.0,"Celebi":0.3280872028,"Arcanine":0.0,"Scizor":0.0,"Piloswine":0.0,"Alakazam":0.0,"Zapdos":0.0,"Venusaur":0.0,"Electrode":0.0,"Articuno":0.0,"Kingdra":0.0482071607},"usage":0.0114077,"Items":{"blackglasses":0.0,"leftovers":1.5159491646,"goldberry":0.0,"berserkgene":0.0,"blackbelt":0.0,"nothing":0.0,"brightpowder":0.0},"Raw count":162,"Spreads":{"Serious:252\/252\/252\/252\/252\/252":1.5159491646,"Serious:252\/0\/252\/252\/252\/252":0.0},"Happiness":{"255":1.5159491646},"Viability Ceiling":[11,75,75,62]},"Celebi":{"Moves":{"":0.0,"detect":0.0,"rest":0.0,"mudslap":0.0,"hiddenpowerelectric":0.0,"hiddenpowerfire":0.0,"hiddenpowerfighting":0.0,"recover":3.0573373726,"curse":0.0,"hiddenpowerice":0.0,"gigadrain":0.0,"psychic":0.5041557649,"batonpass":2.8737022589,"hiddenpowerdark":0.0,"healbell":5.9310396314,"frustration":0.0,"hiddenpowergrass":0.0,"toxic":1.0571727899,"return":0.0,"dreameater":0.0,"leechseed":5.9271039928,"solarbeam":0.0,"ancientpower":2.7015693354,"hyperbeam":0.0,"psychup":0.0,"hiddenpowerbug":0.0,"protect":0.0,"sunnyday":0.0,"futuresight":0.0,"shadowball":0.0,"hiddenpowerrock":0.0,"perishsong":1.6720773799},"Checks and Counters":{},"Abilities":{"noability":5.9310396314},"Teammates":{"Golem":0.0,"Moltres":0.0,"Quagsire":0.0,"Cloyster":0.0,"Dragonite":0.0,"Gyarados":0.0,"Jynx":0.0,"Vaporeon":0.0,"Tyranitar":2.7015693354,"Snorlax":0.9748781859,"Raikou":0.0,"Kangaskhan":0.0,"Smoochum":0.0,"Nidoking":0.0,"Machamp":0.0,"Marowak":0.0,"Charizard":0.0039356387,"Porygon2":0.0,"Ampharos":0.0,"Miltank":0.0,"Pikachu":0.0,"Mew":0.0726569428,"Shuckle":0.0,"Mewtwo":3.6261876674,"Rhydon":0.0,"Chansey":0.0,"Exeggutor":0.0,"Jumpluff":0.0,"Skarmory":0.0,"Nidoqueen":0.0,"Blissey":0.0,"empty":0.0,"Girafarig":0.0,"Smeargle":0.0039356387,"Ditto":0.0,"Aerodactyl":0.0,"Starmie":0.0,"Tauros":0.0,"Meganium":0.0,"Entei":0.0,"Steelix":0.9485454584,"Misdreavus":0.5741340403,"Houndoom":0.0223970889,"Jolteon":0.0,"Feraligatr":0.0,"Crobat":0.0,"Lugia":2.7478935506,"Gengar":0.0,"Magneton":0.0,"Typhlosion":0.0,"Ho-Oh":0.3280872028,"Scyther":0.0,"Suicune":0.0039356387,"Umbreon":0.3280872028,"Arcanine":0.0,"Scizor":0.0,"Heracross":0.0,"Alakazam":0.0,"Donphan":0.0,"Zapdos":0.0,"Hitmontop":0.0,"Kingdra":2.7015693354,"Electrode":0.0,"Articuno":0.0,"Forretress":3.3444246798},"usage":0.0704408,"Items":{"miracleberry":0.0,"greatball":0.0,"leftovers":5.9310396314,"goldberry":0.0,"hardstone":0.0,"twistedspoon":0.0,"berserkgene":0.0,"waterstone":0.0,"blackbelt":0.0,"nothing":0.0,"miracleseed":0.0,"brightpowder":0.0},"Raw count":597,"Spreads":{"Serious:252\/252\/252\/252\/252\/252":5.9310396314,"Serious:252\/0\/252\/252\/252\/252":0.0,"Serious:252\/200\/252\/252\/252\/252":0.0},"Happiness":{"0":0.0,"255":5.9310396314},"Viability Ceiling":[55,75,75,56]},"Forretress":{"Moves":{"":0.0,"hiddenpowersteel":0.0,"rest":0.2556678688,"hiddenpowerfire":11.0161841163,"hiddenpowerghost":1.6843552433,"return":0.0,"substitute":0.0,"pinmissile":0.0,"curse":3.6642252113,"gigadrain":0.5247844835,"sleeptalk":0.2556678688,"toxic":5.5822770005,"explosion":23.4162945945,"reflect":0.0,"hiddenpowerflying":0.0,"rollout":0.0,"hiddenpowerbug":9.3196980447,"protect":0.0,"spikes":24.5786177647,"headbutt":0.0,"doubleedge":0.0,"rapidspin":19.0393703375},"Checks and Counters":{},"Abilities":{"noability":24.8342856334},"Teammates":{"Golem":0.0,"Voltorb":0.0,"Weezing":0.0,"Jolteon":0.0,"Quagsire":0.0,"Cloyster":0.0,"Vaporeon":1.7725748277,"Golbat":0.0,"Tyranitar":11.1881336273,"Snorlax":18.4645078199,"Raikou":1.2058523471,"Kangaskhan":0.0,"Muk":0.0,"Machamp":0.0,"Marowak":0.0348388367,"Lugia":9.7739250461,"Charizard":0.0,"Porygon2":0.0,"Crobat":0.0,"Jynx":0.0,"Shuckle":0.0,"Mewtwo":21.4149242349,"Rhydon":0.0,"Mew":4.8292554553,"Exeggutor":0.0,"Jumpluff":0.0,"Bellossom":0.0,"Blissey":5.6480852175,"Smeargle":0.0,"Ditto":0.0,"Aerodactyl":0.0,"Starmie":0.0,"Meganium":0.0,"Tentacruel":0.0,"Lanturn":0.0,"Miltank":0.0,"Houndoom":0.0223970889,"Gengar":8.6817772404,"Steelix":6.008211015,"Misdreavus":0.6089728771,"Pineco":0.0,"Golduck":0.0,"Ho-Oh":0.5508391636,"Scyther":0.0,"Suicune":0.0,"Umbreon":0.0,"Celebi":3.3444246798,"Scizor":0.0,"Piloswine":0.0,"Skarmory":0.0,"Heracross":0.0,"Feraligatr":0.0,"Zapdos":11.0559534381,"Electrode":0.0,"Kingdra":2.7015693354},"usage":0.411198,"Items":{"mintberry":0.0,"brightpowder":0.2556678688,"focusband":0.0,"silverpowder":0.0,"leftovers":24.4120862158,"goldberry":0.0,"quickclaw":0.0,"nothing":0.0,"miracleberry":0.1665315488,"kingsrock":0.0,"pinkbow":0.0},"Raw count":831,"Spreads":{"Serious:251\/251\/248\/251\/251\/251":0.0,"Serious:252\/252\/252\/252\/252\/252":24.8342856334},"Happiness":{"255":24.8342856334},"Viability Ceiling":[54,84,84,69]},"Skarmory":{"Moves":{"":0.0,"hiddenpowerbug":0.0,"protect":0.0,"curse":0.0482071607,"hiddenpowerice":0.0,"skyattack":0.0,"drillpeck":0.0482071607,"agility":0.0,"rest":0.0482071607,"thief":0.0,"sleeptalk":0.0,"detect":0.0,"hiddenpowerfire":0.0,"pursuit":0.0,"hiddenpowerfighting":0.0,"steelwing":0.0,"toxic":0.0,"mudslap":0.0,"whirlwind":0.0482071607},"Checks and Counters":{},"Abilities":{"noability":0.0482071607},"Teammates":{"Golem":0.0,"Jolteon":0.0,"Quagsire":0.0,"Cloyster":0.0482071607,"Vaporeon":0.0,"Tyranitar":0.0,"Snorlax":0.0,"Raikou":0.0,"Stantler":0.0,"Machamp":0.0,"Marowak":0.0,"Charizard":0.0,"Miltank":0.0,"Pikachu":0.0,"Scizor":0.0,"Shuckle":0.0,"Mewtwo":0.0,"Rhydon":0.0,"Mew":0.0,"Exeggutor":0.0,"Blissey":0.0,"Politoed":0.0,"Granbull":0.0,"Smeargle":0.0,"Ditto":0.0,"Zapdos":0.0,"Entei":0.0482071607,"Misdreavus":0.0,"Lapras":0.0,"Houndoom":0.0,"Gengar":0.0482071607,"Lugia":0.0,"Snubbull":0.0,"Ho-Oh":0.0,"Scyther":0.0,"Suicune":0.0,"Umbreon":0.0482071607,"Celebi":0.0,"Forretress":0.0,"Togetic":0.0,"empty":0.0,"Heracross":0.0,"Slowking":0.0,"Kingdra":0.0482071607},"usage":0.0009237,"Items":{"leftovers":0.0482071607,"scopelens":0.0,"mintberry":0.0},"Raw count":140,"Spreads":{"Serious:252\/252\/252\/252\/252\/252":0.0482071607},"Happiness":{"0":0.0,"255":0.0482071607},"Viability Ceiling":[16,84,84,62]},"Zapdos":{"Moves":{"hiddenpowersteel":0.0,"hiddenpowerwater":13.7356434198,"drillpeck":0.0,"rest":16.1603445821,"hiddenpowerfire":2.7687981181,"hiddenpowerfighting":0.0,"return":0.0,"substitute":1.0113478279,"curse":0.0,"hiddenpowerice":0.5247844835,"thunder":17.5796550399,"thunderwave":1.8631424649,"sleeptalk":16.1603445821,"hiddenpowergrass":1.8480590319,"toxic":0.0,"swagger":0.0,"agility":0.0,"thunderbolt":1.4551798349,"steelwing":0.0,"reflect":0.0,"detect":0.0,"thundershock":0.0,"lightscreen":0.0,"hyperbeam":0.0,"hiddenpowerbug":0.0,"protect":0.0,"hiddenpowerground":0.0,"zapcannon":0.0,"roar":3.0320401144,"skyattack":0.0,"endure":0.0,"doubleedge":0.0,"whirlwind":0.0},"Checks and Counters":{},"Abilities":{"noability":19.0348348749},"Teammates":{"Golem":0.0,"Moltres":0.0,"Quagsire":0.0,"Cloyster":2.5982042738,"Dragonite":0.0,"Vaporeon":0.8270549388,"Tyranitar":11.0340100912,"Snorlax":17.1373940852,"Raikou":0.0,"Muk":0.0,"Machamp":0.0,"Marowak":0.0,"Charizard":0.0,"Chansey":0.0,"Mewtwo":16.7208519927,"Rhydon":0.0,"Mew":8.5614893775,"Exeggutor":0.0,"Skarmory":0.0,"Blissey":0.0,"empty":0.0,"Jolteon":0.0,"Smeargle":0.0,"Ditto":0.0,"Aerodactyl":0.0,"Starmie":0.0,"Heracross":0.0,"Steelix":5.5869986152,"Misdreavus":0.0,"Houndoom":0.0,"Gengar":8.6817772404,"Feraligatr":0.0,"Lugia":3.0666942809,"Nidoqueen":0.0,"Magneton":0.0,"Typhlosion":0.0,"Ho-Oh":0.4165420925,"Suicune":0.0,"Umbreon":0.0,"Celebi":0.0,"Forretress":11.0559534381,"Scizor":0.0,"Alakazam":0.0,"Nidoking":0.0,"Meganium":0.0,"Hitmontop":0.0,"Articuno":0.0,"Blastoise":0.0},"usage":0.3283529,"Items":{"scopelens":0.0,"leftovers":19.0348348749,"magnet":0.0,"berserkgene":0.0,"nothing":0.0,"brightpowder":0.0,"kingsrock":0.0},"Raw count":815,"Spreads":{"Serious:252\/252\/252\/252\/252\/252":18.6182927824,"Serious:252\/0\/252\/252\/252\/252":0.4165420925},"Happiness":{"102":0.0,"255":19.0348348749},"Viability Ceiling":[56,83,83,64]},"Kingdra":{"Moves":{"icywind":0.0,"hiddenpowerdragon":0.0,"blizzard":0.0,"rest":2.7497764961,"hiddenpowerelectric":0.0,"hiddenpowerfire":0.0,"icebeam":0.0,"dragonbreath":2.7497764961,"leer":0.0,"sleeptalk":2.7497764961,"hiddenpowerdark":0.0,"haze":0.0,"frustration":0.0,"toxic":0.0,"twister":0.0,"surf":2.7497764961,"agility":0.0,"waterfall":0.0,"hydropump":0.0,"hyperbeam":0.0,"protect":0.0,"skullbash":0.0},"Checks and Counters":{},"Abilities":{"noability":2.7497764961},"Teammates":{"Cloyster":0.0482071607,"Dragonite":0.0,"Gyarados":0.0,"Fearow":0.0,"Vaporeon":0.0,"Tyranitar":2.7015693354,"Snorlax":0.0,"Ursaring":0.0,"Xatu":0.0,"Machamp":0.0,"Marowak":0.0,"Haunter":0.0,"Charizard":0.0,"Ariados":0.0,"Mewtwo":2.7015693354,"Mew":0.0,"Skarmory":0.0482071607,"Blissey":0.0,"empty":0.0,"Smeargle":0.0,"Aerodactyl":0.0,"Starmie":0.0,"Entei":0.0482071607,"Steelix":0.0,"Houndoom":0.0,"Gengar":0.0482071607,"Lugia":2.7015693354,"Wobbuffet":0.0,"Magneton":0.0,"Typhlosion":0.0,"Ho-Oh":0.0,"Suicune":0.0,"Umbreon":0.0482071607,"Celebi":2.7015693354,"Forretress":2.7015693354,"Scizor":0.0,"Alakazam":0.0,"Donphan":0.0,"Heracross":0.0},"usage":0.0526858,"Items":{"mintberry":0.0,"brightpowder":0.0,"leftovers":2.7497764961,"mysticwater":0.0,"nothing":0.0,"miracleberry":0.0,"kingsrock":0.0},"Raw count":36,"Spreads":{"Serious:252\/252\/252\/252\/252\/252":2.7497764961,"Serious:252\/0\/252\/252\/252\/252":0.0},"Happiness":{"0":0.0,"255":2.7497764961},"Viability Ceiling":[4,72,72,72]}}}